coffeebuzz.py
coffeebuzz-1.0.0.dist-info/DESCRIPTION.rst
coffeebuzz-1.0.0.dist-info/METADATA
coffeebuzz-1.0.0.dist-info/RECORD
coffeebuzz-1.0.0.dist-info/WHEEL
coffeebuzz-1.0.0.dist-info/metadata.json
coffeebuzz-1.0.0.dist-info/top_level.txt
